git_pulsar/__init__.py
git_pulsar/cli.py
git_pulsar/constants.py
git_pulsar/daemon.py
git_pulsar/git_wrapper.py
git_pulsar/ops.py
git_pulsar/service.py
git_pulsar/system.py
git_pulsar-0.12.1.dist-info/METADATA
git_pulsar-0.12.1.dist-info/WHEEL
git_pulsar-0.12.1.dist-info/entry_points.txt
git_pulsar-0.12.1.dist-info/licenses/LICENSE
git_pulsar-0.12.1.dist-info/RECORD
