Metadata-Version: 2.4
Name: git-pulsar
Version: 0.12.1
Summary: Automated, paranoid git backups for students and casual coding.
Author-email: jackson.ferguson0@gmail.com
License-File: LICENSE
Requires-Python: >=3.12
Requires-Dist: rich>=14.2.0
